influenzanet/surveys/__init__.py
influenzanet/surveys/context.py
influenzanet/surveys/html.py
influenzanet/surveys/readable.py
influenzanet/surveys/utils.py
influenzanet/surveys/version.py
influenzanet/surveys/influenzanet/__init__.py
influenzanet/surveys/influenzanet/dictionnary.py
influenzanet/surveys/influenzanet/loader.py
influenzanet/surveys/influenzanet/parser.py
influenzanet/surveys/influenzanet/py.typed
influenzanet/surveys/influenzanet/render.py
influenzanet/surveys/influenzanet/responses.py
influenzanet/surveys/influenzanet/survey.py
influenzanet/surveys/influenzanet/time.py
influenzanet/surveys/influenzanet/translatable.py
influenzanet/surveys/influenzanet/expression/__init__.py
influenzanet/surveys/influenzanet/expression/expressions.json
influenzanet/surveys/influenzanet/expression/library.py
influenzanet/surveys/influenzanet/expression/model.py
influenzanet/surveys/influenzanet/expression/parser.py
influenzanet/surveys/influenzanet/expression/readable.py
influenzanet/surveys/influenzanet/expression/types.py
influenzanet/surveys/preview/__init__.py
influenzanet/surveys/preview/models.py
influenzanet/surveys/preview/schema.py
influenzanet/surveys/repository/__init__.py
influenzanet/surveys/standard/__init__.py
influenzanet/surveys/standard/models.py
influenzanet/surveys/standard/parser.py
influenzanet/surveys/templates/__init__.py
influenzanet/surveys/templates/html/__init__.py
influenzanet/surveys/templates/html/base.html
influenzanet/surveys/templates/html/survey.css
influenzanet/surveys/templates/html/survey.html
influenzanet/surveys/tools/__init_.py
influenzanet/surveys/tools/validator.py
influenzanet/surveys/tools/checker/__init__.py
influenzanet/surveys/tools/checker/checker.py
influenzanet/surveys/tools/checker/tests/__init__.py
influenzanet/surveys/tools/checker/tests/checker.py
influenzanet_surveys-1.2.0.dist-info/licenses/LICENCE
influenzanet_surveys-1.2.0.dist-info/METADATA
influenzanet_surveys-1.2.0.dist-info/WHEEL
influenzanet_surveys-1.2.0.dist-info/top_level.txt
influenzanet_surveys-1.2.0.dist-info/RECORD
