Metadata-Version: 2.4
Name: influenzanet.surveys
Version: 1.2.0
Summary: Influenzanet surveys management library
Author-email: Clement Turbelin <clement.turbelin@iplesp.upmc.fr>
License: Apache-2.0
Project-URL: Homepage, https://github.com/influenzanet/python-influenzanet-surveys
Project-URL: Bug Tracker, https://github.com/influenzanet/python-influenzanet-surveys/issues
Keywords: influenzanet,surveys
Classifier: Programming Language :: Python :: 3
Classifier: Operating System :: OS Independent
Classifier: Topic :: Scientific/Engineering :: Medical Science Apps.
Requires-Python: >=3.9
License-File: LICENCE
Requires-Dist: jinja2==3
Requires-Dist: jsonschema==4.*
Requires-Dist: requests==2.*
Provides-Extra: validator
Requires-Dist: PyYAML==6.0.1; extra == "validator"
Dynamic: license-file
